pyconfigreader/__init__.py
pyconfigreader/exceptions.py
pyconfigreader/reader.py
pyconfigreader-0.10.0.dist-info/LICENSE
pyconfigreader-0.10.0.dist-info/METADATA
pyconfigreader-0.10.0.dist-info/WHEEL
pyconfigreader-0.10.0.dist-info/top_level.txt
pyconfigreader-0.10.0.dist-info/RECORD
