Metadata-Version: 2.1
Name: pyconfigreader
Version: 0.10.0
Summary: A module for handling simple configuration requirements
Home-page: http://github.com/giantas/pyconfigreader
Author: Aswa Paul
License: MIT
Platform: UNKNOWN
Classifier: Programming Language :: Python
Classifier: Programming Language :: Python :: 3
Classifier: Programming Language :: Python :: 3.5
Classifier: Programming Language :: Python :: 3.6
Classifier: Programming Language :: Python :: 3.7
Classifier: Programming Language :: Python :: 3.8
Classifier: Programming Language :: Python :: 3.9
Requires-Python: >3.4, <3.10
License-File: LICENSE
